changelog.py
evative7_changeloggen-0.0.5.dist-info/licenses/LICENSE
evative7_changeloggen-0.0.5.dist-info/METADATA
evative7_changeloggen-0.0.5.dist-info/WHEEL
evative7_changeloggen-0.0.5.dist-info/entry_points.txt
evative7_changeloggen-0.0.5.dist-info/top_level.txt
evative7_changeloggen-0.0.5.dist-info/RECORD
