Metadata-Version: 2.4
Name: evative7-changeloggen
Version: 0.0.5
Summary: Generate changelog based on git commit
Author: EvATive7
Project-URL: Homepage, https://github.com/EvATive7/evative7-changeloggen
Classifier: Programming Language :: Python :: 3
Classifier: Operating System :: OS Independent
Requires-Python: >=3.6
License-File: LICENSE
Provides-Extra: dev
Requires-Dist: black; extra == "dev"
Requires-Dist: isort; extra == "dev"
Requires-Dist: flake8; extra == "dev"
Requires-Dist: pytest; extra == "dev"
Requires-Dist: pre-commit; extra == "dev"
Provides-Extra: build
Requires-Dist: build; extra == "build"
Dynamic: license-file
